README.md
setup.cfg
setup.py
veracode/__init__.py
veracode/application.py
veracode/build.py
veracode/exceptions.py
veracode/log.py
veracode/sandbox.py
veracode/user.py
veracode/API/__init__.py
veracode/API/admin.py
veracode/API/core.py
veracode/API/exceptions.py
veracode/API/flawreport.py
veracode/API/mitigation.py
veracode/API/results.py
veracode/API/sandbox.py
veracode/API/upload.py
veracode/SDK/__init__.py
veracode/SDK/admin.py
veracode/SDK/core.py
veracode/SDK/exceptions.py
veracode/SDK/flawreport.py
veracode/SDK/mitigation.py
veracode/SDK/results.py
veracode/SDK/sandbox.py
veracode/SDK/upload.py
veracode/SDK/utils.py
veracode/utils/__init__.py
veracode/utils/cli.py
veracode/utils/app/__init__.py
veracode/utils/app/commands.py
veracode/utils/report/__init__.py
veracode/utils/report/commands.py
veracode/utils/sandbox/__init__.py
veracode/utils/sandbox/commands.py
veracode/utils/user/__init__.py
veracode/utils/user/commands.py
veracode_python.egg-info/PKG-INFO
veracode_python.egg-info/SOURCES.txt
veracode_python.egg-info/dependency_links.txt
veracode_python.egg-info/entry_points.txt
veracode_python.egg-info/requires.txt
veracode_python.egg-info/top_level.txt