Metadata-Version: 2.1
Name: veracode-python
Version: 0.1.67
Summary: Python wrapper for the Veracode XML APIs
Home-page: https://github.com/chuckorde/veracode-python
Author: Chuck Orde
Author-email: chuckorde@gmail.com
License: BSD-3-Clause
Download-URL: https://github.com/chuckorde/veracode-python/archive/v0.1.67/.tar.gz
Platform: UNKNOWN
Classifier: Development Status :: 3 - Alpha
Classifier: Intended Audience :: Developers
Classifier: License :: OSI Approved :: BSD License
Classifier: Programming Language :: Python :: 3.5
Classifier: Programming Language :: Python :: 3.6
Classifier: Programming Language :: Python :: 3.7
Classifier: Programming Language :: Python :: 3.8
Requires-Python: >= 3.5
